llm_tool_store/__init__.py
llm_tool_store/main.py
llm_tool_store-0.1.1.dist-info/METADATA
llm_tool_store-0.1.1.dist-info/WHEEL
llm_tool_store-0.1.1.dist-info/RECORD
